micrometa/__init__.py
micrometa/dataset.py
micrometa/experiment.py
micrometa/fluoview.py
micrometa/imagej.py
micrometa/log.py
python_micrometa-15.2.3.dist-info/METADATA
python_micrometa-15.2.3.dist-info/WHEEL
python_micrometa-15.2.3.dist-info/RECORD
