Metadata-Version: 2.1
Name: python-micrometa
Version: 15.2.3
Summary: Process metadata from various light-microscopy related formats.
Home-page: https://github.com/imcf/python-micrometa
Keywords: fiji,jython,imagej,microscopy,metadata
Author: Niko Ehrenfeuchter
Author-email: nikolaus.ehrenfeuchter@unibas.ch
Requires-Python: >=2.7, !=3.0.*, !=3.1.*, !=3.2.*, !=3.3.*
Classifier: Programming Language :: Python :: 2
Classifier: Programming Language :: Python :: 2.7
Classifier: Programming Language :: Python :: 3
Classifier: Programming Language :: Python :: 3.4
Classifier: Programming Language :: Python :: 3.5
Classifier: Programming Language :: Python :: 3.6
Classifier: Programming Language :: Python :: 3.7
Classifier: Programming Language :: Python :: 3.8
Classifier: Programming Language :: Python :: 3.9
Classifier: Programming Language :: Python :: 3.10
Classifier: Programming Language :: Python :: 3.11
Classifier: Programming Language :: Python :: 3.12
Requires-Dist: imcflibs (<3.0)
Requires-Dist: imcflibs (>=1.4)
Requires-Dist: olefile (>=0.46,<0.47)
Project-URL: Repository, https://github.com/imcf/python-micrometa
